tclivalidator/__init__.py
tclivalidator/validator.py
tclivalidator/console/__init__.py
tclivalidator/console/console_scripts.py
tclivalidator/data/spec/__init__.py
tclivalidator/data/spec/103120/1.1.1/xsd/TS_103_280_v111.xsd
tclivalidator/data/spec/103120/1.1.1/xsd/config.json
tclivalidator/data/spec/103120/1.1.1/xsd/ts_103120_Authorisation.xsd
tclivalidator/data/spec/103120/1.1.1/xsd/ts_103120_Common.xsd
tclivalidator/data/spec/103120/1.1.1/xsd/ts_103120_Core.xsd
tclivalidator/data/spec/103120/1.1.1/xsd/ts_103120_Document.xsd
tclivalidator/data/spec/103120/1.1.1/xsd/ts_103120_LITask.xsd
tclivalidator/data/spec/103120/1.1.1/xsd/ts_103120_Notification.xsd
tclivalidator/data/spec/103120/1.10.1/xsd/TS_103_280.xsd
tclivalidator/data/spec/103120/1.10.1/xsd/config.json
tclivalidator/data/spec/103120/1.10.1/xsd/ts_103120_Authorisation.xsd
tclivalidator/data/spec/103120/1.10.1/xsd/ts_103120_Common.xsd
tclivalidator/data/spec/103120/1.10.1/xsd/ts_103120_Core.xsd
tclivalidator/data/spec/103120/1.10.1/xsd/ts_103120_Delivery.xsd
tclivalidator/data/spec/103120/1.10.1/xsd/ts_103120_Document.xsd
tclivalidator/data/spec/103120/1.10.1/xsd/ts_103120_Notification.xsd
tclivalidator/data/spec/103120/1.10.1/xsd/ts_103120_Task.xsd
tclivalidator/data/spec/103120/1.11.1/xsd/TS_103_280.xsd
tclivalidator/data/spec/103120/1.11.1/xsd/config.json
tclivalidator/data/spec/103120/1.11.1/xsd/ts_103120_Authorisation.xsd
tclivalidator/data/spec/103120/1.11.1/xsd/ts_103120_Common.xsd
tclivalidator/data/spec/103120/1.11.1/xsd/ts_103120_Core.xsd
tclivalidator/data/spec/103120/1.11.1/xsd/ts_103120_Delivery.xsd
tclivalidator/data/spec/103120/1.11.1/xsd/ts_103120_Document.xsd
tclivalidator/data/spec/103120/1.11.1/xsd/ts_103120_Notification.xsd
tclivalidator/data/spec/103120/1.11.1/xsd/ts_103120_Task.xsd
tclivalidator/data/spec/103120/1.11.2/xsd/TS_103_280.xsd
tclivalidator/data/spec/103120/1.11.2/xsd/config.json
tclivalidator/data/spec/103120/1.11.2/xsd/ts_103120_Authorisation.xsd
tclivalidator-0.1a5.dist-info/entry_points.txt
tclivalidator-0.1a5.dist-info/LICENSE
tclivalidator-0.1a5.dist-info/WHEEL
tclivalidator-0.1a5.dist-info/METADATA
tclivalidator-0.1a5.dist-info/RECORD
