Metadata-Version: 2.1
Name: tclivalidator
Version: 0.1a5
Summary: tclivalidator
Author-email: Mark Canterbury <markc@tencastle.com>
Requires-Python: >=3.12
Classifier: License :: OSI Approved :: MIT License
Requires-Dist: semver
Requires-Dist: rich >= 13.7.0
Requires-Dist: typer
